Workbook

Sheet Sheet5
A3: Row Labels | B3: Sum of Amount
A4: 2012 | B4: -667051.46
A5: 2013 | B5: -315064.99
A6: 2014 | B6: -383809.58
A7: 2015 | B7: -635753.28
A8: 2016 | B8: -585556.32
A9: 2017 | B9: -932299.65
A10: 2018 | B10: -1003099.7
A11: 2019 | B11: -787099.83
A12: 2020 | B12: -861234.78
A13: 2021 | B13: -505258.08
A14: 2022 | B14: -1190742.8
A15: 2023 | B15: -568545.9
A16: 2024 | B16: -483693.96
A17: Grand Total | B17: -8919210.4

Sheet Sheet6
A3: Row Labels | B3: Count of Year
A4: 2002 | B4: 137
A5: 2003 | B5: 113
A6: 2004 | B6: 196
A7: 2005 | B7: 150
A8: 2006 | B8: 249
A9: 2007 | B9: 106
A10: 2008 | B10: 73
A11: 2009 | B11: 30
A12: 2010 | B12: 303
A13: 2011 | B13: 166
A14: 2012 | B14: 1045
A15: 2013 | B15: 690
... A26: 2024 | B26: 427
A27: Grand Total | B27: 13284

Sheet Report
A1: Itemized Categories - All Dates
A3: 8/12/1996 through 2/1/2025 (Cash Basis)
B5: Date | C5: Account | D5: Num | E5: Description | F5: Memo | G5: Tag | H5: Clr | I5: Amount | J5: Amount | K5: Amount | O5: Amount | P5: Year
B8: EXPENSES | I8: -9240773.5 | J8: -9240773.5 | K8: -9240773.5
B9: TT Renovations | I9: -9240773.5 | J9: -9240773.5 | K9: -9240773.5
B10: TT Renovations:4039 Central | I10: -7538.26 | J10: -7538.26 | K10: -7538.26
B11: 37284 | C11: Marvel MC | D11: DC | E11: Lowe's | H11: R | I11: -25.05 | J11: -25.05 | K11: -25.05
B12: 37286 | C12: Cash | E12: Roof Repair | I12: 800 | K12: 800
B13: 37294 | C13: Marvel MC | D13: DC | E13: BMV | F13: truck plates - pay all due to inspection | H13: R | I13: -190.75 | J13: -190.75 | K13: -190.75
B14: 37305 | C14: Marvel MC | E14: Dave's Trucking | F14: dumpster | H14: R | I14: -270 | J14: -270 | K14: -270 | M14: Row Labels | N14: Count of Tag | P14: {=YEAR(B14:B14342)} -> 2002 | R14: Row Labels | T14: Row Labels | U14: Count of 2012 | W14: Row Labels | X14: Sum of Amount
B15: TT Renovations:47th St. | I15: 63871.02 | J15: =SUM(J16:J69) -> -45885.09 | K15: 63871.02 | M15: ADDITIONAL WORK | N15: 9 | P15: #VALUE! | R15: 1900 | T15: 1900 | U15: 786 | W15: 1900 | X15: -215859.32
A16: TT Renovations:47th St. | B16: 37307 | C16: Marvel MC | D16: DC | E16: Lowe's | H16: R | I16: -155.04 | J16: -155.04 | K16: -155.04 | M16: APPLIANCE INSTALL | N16: 96 | P16: 2002 | R16: 2002 | T16: 2002 | U16: 137 | W16: 2002 | X16: 16669.82
A17: TT Renovations:47th St. | B17: 37308 | C17: Marvel MC | D17: DC | E17: Lowe's | H17: R | I17: -30.2 | J17: -30.2 | K17: -30.2 | M17: APPLIANCES | N17: 14 | P17: 2002 | R17: 2003 | T17: 2003 | U17: 113 | W17: 2003 | X17: -19618.68
A18: TT Renovations:47th St. | B18: 37308 | C18: Marvel MC | D18: DC | E18: Lowe's | H18: R | I18: -534.41 | J18: -534.41 | K18: -534.41 | M18: ARCHITECT | N18: 5 | P18: 2002 | R18: 2004 | T18: 2004 | U18: 196 | W18: 2004 | X18: -22174.06
A19: TT Renovations:47th St. | B19: 37308 | C19: Marvel MC | E19: Reese Kitchens | H19: R | I19: -744.45 | J19: -744.45 | K19: -744.45 | M19: ASBESTOS REMOVAL | N19: 17 | P19: 2002 | R19: 2005 | T19: 2005 | U19: 150 | W19: 2005 | X19: 7101.03
A20: TT Renovations:47th St. | B20: 37309 | C20: Marvel MC | D20: DC | E20: Lowe's | H20: R | I20: -5.4 | J20: -5.4 | K20: -5.4 | M20: ASPHALT | N20: 2 | P20: 2002 | R20: 2006 | T20: 2006 | U20: 249 | W20: 2006 | X20: -11272.94
A21: TT Renovations:47th St. | B21: 37315 | C21: Marvel MC | D21: DC | E21: Lowe's | H21: R | I21: -110.9 | J21: -110.9 | K21: -110.9 | M21: BACKSPLASH | N21: 19 | P21: 2002 | R21: 2007 | T21: 2007 | U21: 106 | W21: 2007 | X21: 85972.11
A22: TT Renovations:47th St. | B22: 37316 | C22: Marvel MC | D22: DC | E22: Lowe's | H22: R | I22: -47.22 | J22: -47.22 | K22: -47.22 | M22: BASEMENT WATERPROOFING | N22: 4 | P22: 2002 | R22: 2008 | T22: 2008 | U22: 73 | W22: 2008 | X22: -31696.21
A23: TT Renovations:47th St. | B23: 37317 | C23: Huntington Checking-Ralston Checking | D23: DEP S | E23: Allied Services | H23: R | I23: 976.04 | K23: 976.04 | M23: CABINET BUILD | N23: 318 | P23: 2002 | R23: 2009 | T23: 2009 | U23: 30 | W23: 2009 | X23: 3690.25
A24: TT Renovations:47th St. | B24: 37317 | C24: Huntington Checking-Ralston Checking | D24: 1 | E24: Theresa Tetrault | F24: drywall/travis | H24: R | I24: -250 | J24: -250 | K24: -250 | M24: CABINETRY | N24: 32 | P24: 2002 | R24: 2010 | T24: 2010 | U24: 303 | W24: 2010 | X24: -35353.34
A25: TT Renovations:47th St. | B25: 37317 | C25: Huntington Checking-Ralston Checking | D25: 3 | E25: Theresa Tetrault | F25: truck ins/gas/lowe's/travis | H25: R | I25: -202.31 | J25: -202.31 | K25: -202.31 | M25: CABINETRY INSTALL | N25: 126 | P25: 2002 | R25: 2011 | T25: 2011 | U25: 166 | W25: 2011 | X25: -18019.41
A26: TT Renovations:47th St. | B26: 37317 | C26: Cash | E26: Gerry Sanders | F26: 1/2 drywall | I26: -315 | J26: -315 | K26: -315 | M26: CARPENTRY | N26: 64 | P26: 2002 | R26: 2012 | T26: 2012 | U26: 1044 | W26: 2012 | X26: -667051.46
A27: TT Renovations:47th St. | B27: 37319 | C27: Marvel MC | D27: DC | E27: Lowe's | H27: R | I27: -98.54 | J27: -98.54 | K27: -98.54 | M27: CARPET | N27: 10 | P27: 2002 | R27: 2013 | T27: 2013 | U27: 690 | W27: 2013 | X27: -315064.99
A28: TT Renovations:47th St. | B28: 37320 | C28: Marvel MC | D28: DC | E28: Lowe's | H28: R | I28: -8.06 | J28: -8.06 | K28: -8.06 | M28: CLEANUP | N28: 9 | P28: 2002 | R28: 2014 | T28: 2014 | U28: 976 | W28: 2014 | X28: -383809.58
A29: TT Renovations:47th St. | B29: 37320 | C29: Marvel MC | D29: DC | E29: Lowe's | H29: R | I29: -23.15 | J29: -23.15 | K29: -23.15 | M29: CLOSET SHELVING | N29: 9 | P29: 2002 | R29: 2015 | T29: 2015 | U29: 1392 | W29: 2015 | X29: -635753.28
A30: TT Renovations:47th St. | B30: 37321 | C30: Marvel MC | D30: DC | E30: Lowe's | H30: R | I30: -33.5 | J30: -33.5 | K30: -33.5 | M30: CONCRETE | N30: 87 | P30: 2002 | R30: 2016 | T30: 2016 | U30: 1062 | W30: 2016 | X30: -585556.32
A31: TT Renovations:47th St. | B31: 37322 | C31: Marvel MC | D31: DC | E31: Lowe's | H31: R | I31: -89.79 | J31: -89.79 | K31: -89.79 | M31: COUNTERTOPS | N31: 92 | P31: 2002 | R31: 2017 | T31: 2017 | U31: 1199 | W31: 2017 | X31: -932299.65
A32: TT Renovations:47th St. | B32: 37323 | C32: Marvel MC | D32: DC | E32: Lowe's | H32: R | I32: -139.56 | J32: -139.56 | K32: -139.56 | M32: DECK | N32: 67 | P32: 2002 | R32: 2018 | T32: 2018 | U32: 1220 | W32: 2018 | X32: -1003099.7
A33: TT Renovations:47th St. | B33: 37324 | C33: Marvel MC | D33: DC | E33: Lowe's | H33: R | I33: -87.13 | J33: -87.13 | K33: -87.13 | M33: DECK LABOR | N33: 5 | P33: 2002 | R33: 2019 | T33: 2019 | U33: 1385 | W33: 2019 | X33: -787099.83
A34: TT Renovations:47th St. | B34: 37326 | C34: Marvel MC | E34: Reese Kitchens | H34: R | I34: -744.45 | J34: -744.45 | K34: -744.45 | M34: DELIVERY | N34: 10 | P34: 2002 | R34: 2020 | T34: 2020 | U34: 1057 | W34: 2020 | X34: -861234.78
A35: TT Renovations:47th St. | B35: 37326 | C35: Marvel MC | D35: DC | E35: Lowe's | H35: R | I35: -15 | J35: -15 | K35: -15 | M35: DEMO | N35: 532 | P35: 2002 | R35: 2021 | T35: 2021 | U35: 373 | W35: 2021 | X35: -505258.08
A36: TT Renovations:47th St. | B36: 37326 | C36: Marvel MC | D36: DC | E36: Speedway | H36: R | I36: -17.65 | J36: -17.65 | K36: -17.65 | M36: DEMO:FRAMING | N36: 3 | P36: 2002 | R36: 2022 | T36: 2022 | U36: 487 | W36: 2022 | X36: -1190742.8
A37: TT Renovations:47th St. | B37: 37327 | C37: Huntington Checking-Ralston Checking | D37: 4 | E37: Bud Hindsley | F37: plumbing/travis | H37: R | I37: -697.21 | J37: -697.21 | K37: -697.21 | M37: DOORS | N37: 200 | P37: 2002 | R37: 2023 | T37: 2023 | U37: 448 | W37: 2023 | X37: -568545.9
A38: TT Renovations:47th St. | B38: 37327 | C38: Huntington Checking-Ralston Checking | D38: 5 | E38: Gerry Sanders | F38: painting/travis | H38: R | I38: -200 | J38: -200 | K38: -200 | M38: DRYWALL | N38: 350 | P38: 2002 | R38: 2024 | T38: 2024 | U38: 427 | W38: 2024 | X38: -483693.96
A39: TT Renovations:47th St. | B39: 37327 | C39: Marvel MC | E39: Dave's Trucking | H39: R | I39: -245 | J39: -245 | K39: -245 | M39: DUMP LABOR | N39: 62 | P39: 2002 | R39: 2025 | T39: 2025 | U39: 49 | W39: 2025 | X39: -55458.71
A40: TT Renovations:47th St. | B40: 37331 | C40: Huntington Checking-Ralston Checking | D40: 6 | E40: Bill York | F40: plumbing/travis | H40: R | I40: -80 | J40: -80 | K40: -80 | M40: DUMPSTER | N40: 445 | P40: 2002 | R40: #VALUE! | T40: #VALUE! | U40: 210 | W40: Grand Total | X40: -9215229.9
A41: TT Renovations:47th St. | B41: 37331 | C41: Huntington Checking-Ralston Checking | D41: 101 | E41: Bart Mousa | F41: tile/travis | H41: R | I41: -100 | J41: -100 | K41: -100 | M41: ELEC FINISH MATERIALS | N41: 243 | P41: 2002 | R41: Grand Total | T41: Grand Total | U41: 14328
A42: TT Renovations:47th St. | B42: 37340 | C42: Huntington Checking-Ralston Checking | D42: DEP | E42: Travis Tetrault | H42: R | I42: 780 | K42: 780 | M42: ELEC LABOR | N42: 92 | P42: 2002
A43: TT Renovations:47th St. | B43: 37341 | C43: Huntington Checking-Ralston Checking | D43: 105 | E43: James Warriner | F43: hardwoods/travis | H43: R | I43: -2360 | J43: -2360 | K43: -2360 | M43: ELEC ROUGH MATERIALS | N43: 161 | P43: 2002
A44: TT Renovations:47th St. | B44: 37343 | C44: Huntington Checking-Ralston Checking | D44: DC | E44: Lowe's | H44: R | I44: -17.64 | J44: -17.64 | K44: -17.64 | M44: ELECTRICAL EXTRAS | N44: 250 | P44: 2002
A45: TT Renovations:47th St. | B45: 37343 | C45: Huntington Checking-Ralston Checking | D45: DEP | E45: Travis Tetrault | H45: R | I45: 1180 | K45: 1180 | M45: ELECTRICAL FINISH | N45: 279 | P45: 2002
A46: TT Renovations:47th St. | B46: 37352 | C46: Marvel MC | E46: Dave's Trucking | H46: R | I46: -195 | J46: -195 | K46: -195 | M46: ELECTRICAL FINISH:ELECTRICAL ROUGH | N46: 3 | P46: 2002
A47: TT Renovations:47th St. | B47: 37352 | C47: Marvel MC | E47: Dave's Trucking | F47: sat p/u | H47: R | I47: -25 | J47: -25 | K47: -25 | M47: ELECTRICAL ROUGH | N47: 338 | P47: 2002
A48: TT Renovations:47th St. | B48: 37356 | C48: Marvel MC | D48: DC | E48: Lowe's | F48: courtney | H48: R | I48: -22.93 | J48: -22.93 | K48: -22.93 | M48: ESTIMATE | N48: 6 | P48: 2002
A49: TT Renovations:47th St. | B49: 37362 | C49: Huntington Checking-Ralston Checking | D49: 106 | E49: Bud Hindsley | H49: R | I49: -50 | J49: -50 | K49: -50 | M49: EX TRIM LABOR | N49: 100 | P49: 2002
A50: TT Renovations:47th St. | B50: 37362 | C50: Marvel MC | E50: Flooring | H50: R | I50: -2380 | J50: -2380 | K50: -2380 | M50: EX TRIM MATERIALS | N50: 252 | P50: 2002
A51: TT Renovations:47th St. | B51: 37375 | C51: Huntington Checking-Ralston Checking | D51: DEP | E51: Travis Tetrault | H51: R | I51: 26570 | K51: 26570 | M51: EXCAVATION | N51: 28 | P51: 2002
A52: TT Renovations:47th St. | B52: 37379 | C52: Marvel MC | E52: Ruth's Chris | F52: thanks for helping | H52: R | I52: -189.71 | J52: -189.71 | K52: -189.71 | M52: FENCING | N52: 20 | P52: 2002
A53: TT Renovations:47th St. | B53: 37400 | C53: Huntington Checking-Ralston Checking | D53: DEP S | E53: Travis/Ebay | H53: R | I53: 1550.94 | K53: 1550.94 | M53: FIREPLACE | N53: 6 | P53: 2002
A54: TT Renovations:47th St. | B54: 37420 | C54: Huntington Checking-Ralston Checking | D54: 118 | E54: FC Tucker | F54: Broadway earnest money | H54: R | I54: -1000 | J54: -1000 | K54: -1000 | M54: FIXTURES | N54: 113 | P54: 2002
A55: TT Renovations:47th St. | B55: 37424 | C55: Huntington Checking-Ralston Checking | D55: 120 | E55: Security Home Inspection | F55: inspection | H55: R | I55: -355 | J55: -355 | K55: -355 | M55: FLOORING | N55: 177 | P55: 2002
A56: TT Renovations:47th St. | B56: 37425 | C56: Huntington Checking-Ralston Checking | D56: 121 | E56: Geier & Baroudos | F56: appraisal | H56: R | I56: -275 | J56: -275 | K56: -275 | M56: FOUNDATION | N56: 101 | P56: 2002
A57: TT Renovations:47th St. | B57: 37431 | C57: Huntington Checking-Ralston Checking | D57: 122 | E57: State Farm Insurance | H57: R | I57: -723 | J57: -723 | K57: -723 | M57: FRAME MATERIALS | N57: 563 | P57: 2002
A58: TT Renovations:47th St. | B58: 37432 | C58: Huntington Checking-Ralston Checking | D58: 9999 | E58: Title Services | H58: R | I58: -15326.71 | J58: -15326.71 | K58: -15326.71 | M58: FRAMING | N58: 754 | P58: 2002
A59: TT Renovations:47th St. | B59: 37432 | C59: Huntington Checking-Ralston Checking | D59: DEP | E59: Travis Tetrault | H59: R | I59: 7500 | K59: 7500 | M59: FRAMING:SIDING | N59: 3 | P59: 2002
A60: TT Renovations:47th St. | B60: 37433 | C60: Huntington Checking-Ralston Checking | D60: 123 | E60: Gerry Sanders | H60: R | I60: -150 | J60: -150 | K60: -150 | M60: GARAGE DOOR | N60: 37 | P60: 2002
A61: TT Renovations:47th St. | B61: 37442 | C61: Marvel MC | E61: Reese Kitchens | F61: cabinet balance | H61: R | I61: -2402 | J61: -2402 | K61: -2402 | M61: GLASS BLOCK | N61: 29 | P61: 2002
A62: TT Renovations:47th St. | B62: 37446 | C62: Huntington Checking-Ralston Checking | D62: 126 | E62: Reese Kitchens, Inc. | F62: counter tops | H62: R | I62: -1494.15 | J62: -1494.15 | K62: -1494.15 | M62: GLASS REPAIR | N62: 2 | P62: 2002
A63: TT Renovations:47th St. | B63: 37446 | C63: Huntington Checking-Ralston Checking | D63: 127 | E63: Brown's Flooring | F63: flooring deposit | H63: R | I63: -2300 | J63: -2300 | K63: -2300 | M63: GUTTERING | N63: 57 | P63: 2002
A64: TT Renovations:47th St. | B64: 37448 | C64: Huntington Checking-Ralston Checking | D64: 128 | E64: Gerry Sanders | H64: R | I64: -250 | J64: -250 | K64: -250 | M64: HANDYMAN | N64: 362 | P64: 2002
A65: TT Renovations:47th St. | B65: 37454 | C65: Huntington Checking-Ralston Checking | D65: 129 | E65: Reese Kitchens | F65: cabinet balance | H65: R | I65: -2401 | J65: -2401 | K65: -2401 | M65: HARDWARE | N65: 23 | P65: 2002
A66: TT Renovations:47th St. | B66: 37454 | C66: Huntington Checking-Ralston Checking | D66: 130 | E66: Norandex | F66: windows/doors | H66: R | I66: -2323.98 | J66: -2323.98 | K66: -2323.98 | M66: HVAC | N66: 228 | P66: 2002
A67: TT Renovations:47th St. | B67: 37454 | C67: Huntington Checking-Ralston Checking | D67: 131 | E67: Gerry Sanders | F67: paint | H67: R | I67: -2100 | J67: -2100 | K67: -2100 | M67: INSULATION | N67: 148 | P67: 2002
A68: TT Renovations:47th St. | B68: 37454 | C68: Huntington Checking-Ralston Checking | D68: DEP | E68: Travis Tetrault | F68: windows | H68: R | I68: 2323.98 | K68: 2323.98 | M68: JOBSITE MAINTENANCE | N68: 13 | P68: 2002
A69: TT Renovations:47th St. | B69: 37456 | C69: Home Equity-Home Equity | D69: 1005 | E69: Travis Tetrault | F69: down payment | H69: R | I69: -4570 | J69: -4570 | K69: -4570 | M69: LABOR | N69: 78 | P69: 2002
B70: TT Renovations:Abelard | I70: -3200 | J70: -3200 | K70: -3200 | M70: LANDSCAPING | N70: 17 | P70: #VALUE!
B71: 37459 | C71: Marvel MC | E71: Brown's Floor Covering | H71: R | I71: -2492.27 | J71: -2492.27 | K71: -2492.27 | M71: LAURA S | N71: 28 | P71: 2002
B72: 37464 | C72: Huntington Checking-Ralston Checking | D72: 132 | E72: Indianapolis Water Company | H72: R | I72: -10.03 | J72: -10.03 | K72: -10.03 | M72: MASONRY | N72: 67 | P72: 2002
B73: TT Renovations:Aimee Kandrac | I73: -130530.43 | J73: -130530.43 | K73: -130530.43 | M73: MATERIALS | N73: 1 | P73: #VALUE!
B74: 37464 | C74: Huntington Checking-Ralston Checking | D74: 135 | E74: Indianapolis Power & Light Company | H74: R | I74: -9.99 | J74: -9.99 | K74: -9.99 | M74: METAL WORK | N74: 1 | P74: 2002
B75: 37464 | C75: Huntington Checking-Ralston Checking | D75: 136 | E75: Citizen's Gas | H75: R | I75: -10.94 | J75: -10.94 | K75: -10.94 | M75: MIRRORS | N75: 4 | P75: 2002
B76: 37464 | C76: Huntington Checking-Ralston Checking | D76: DEP | E76: State Farm Insurance | H76: R | I76: 203 | K76: 203 | M76: PAINT | N76: 795 | P76: 2002
B77: 37464 | C77: Huntington Checking-Ralston Checking | D77: 134 | E77: Cingular Wireless | F77: July | H77: R | I77: -33.71 | J77: -33.71 | K77: -33.71 | M77: PAVERS | N77: 10 | P77: 2002
B78: 37468 | C78: Huntington Checking-Ralston Checking | D78: 124 S | E78: State Farm Insurance | H78: R | I78: -165.79 | J78: -165.79 | K78: -165.79 | M78: PERMITS | N78: 243 | P78: 2002
B79: 37470 | C79: Huntington Checking-Ralston Checking | D79: 137 | E79: Jeff Lee | H79: R | I79: -560 | J79: -560 | K79: -560 | M79: PLASTER | N79: 1 | P79: 2002
B80: 37470 | C80: Home Equity-Home Equity | D80: 1006 S | E80: Andy Mohr Ford | H80: R | I80: -1097.13 | J80: -1097.13 | K80: -1097.13 | M80: PLUMB LABOR FINISH | N80: 34 | P80: 2002
B81: 37473 | C81: Huntington Checking-Ralston Checking | D81: 139 | E81: Jeff Lee | F81: tile balance | H81: R | I81: -50 | J81: -50 | K81: -50 | M81: PLUMB LABOR FINISH:PLUMB LABOR ROUGH | N81: 1 | P81: 2002
B82: 37473 | C82: Marvel MC | D82: DC | E82: Lowe's | F82: laminate flooring | H82: R | I82: -467.15 | J82: -467.15 | K82: -467.15 | M82: PLUMB LABOR ROUGH | N82: 41 | P82: 2002
B83: 37474 | C83: Huntington Checking-Ralston Checking | D83: 140 | E83: Bill York | F83: plumbing | H83: R | I83: -270 | J83: -270 | K83: -270 | M83: PLUMB SERVICE | N83: 9 | P83: 2002
B84: 37474 | C84: Home Equity-Home Equity | D84: 1007 | E84: Broad Ripple Tree Service | F84: tree removal | H84: R | I84: -3500 | J84: -3500 | K84: -3500 | M84: PLUMBING ALLOWANCE | N84: 85 | P84: 2002
F85: microwave install | G85: APPLIANCE INSTALL | H85: R | I85: -90 | J85: -90 | K85: -90 | M85: PLUMBING-EXTRAS | N85: 72 | P85: 1900
B86: 37474 | C86: Huntington Checking-Ralston Checking | D86: DC | E86: Amoco | H86: R | I86: -29.05 | J86: -29.05 | K86: -29.05 | M86: PLUMBING-FINISH | N86: 137 | P86: 2002
F87: garbage disposal | G87: APPLIANCE INSTALL | H87: R | I87: -100 | J87: -100 | K87: -100 | M87: PLUMBING-ROUGH | N87: 154 | P87: 1900
B88: 37475 | C88: Marvel MC | E88: Reese Kitchens | F88: countertop balance | H88: R | I88: -1494.15 | J88: -1494.15 | K88: -1494.15 | M88: PORTABLE TOILET | N88: 64 | P88: 2002
B89: 37476 | C89: Marvel MC | E89: Reese Kitchens | F89: vanity top | H89: R | I89: -222.6 | J89: -222.6 | K89: -222.6 | M89: PRINTING | N89: 37 | P89: 2002
F90: dishwasher supply/cord kit | G90: APPLIANCE INSTALL | I90: -47.25 | J90: -47.25 | K90: -47.25 | M90: PROJECT MANAGEMENT | N90: 314 | P90: 1900
B91: 37477 | C91: Marvel MC | D91: DC | E91: Lowe's | F91: faucet,fixtures, door knob | H91: R | I91: -502.72 | J91: -502.72 | K91: -502.72 | M91: RADON | N91: 1 | P91: 2002
F92: vent range hood | G92: APPLIANCE INSTALL | H92: R | I92: -79.7 | J92: -79.7 | K92: -79.7 | M92: REMEDIATION | N92: 4 | P92: 1900
B93: 37478 | C93: Home Equity-Home Equity | D93: 1008 | E93: Rodney Leighty | F93: exterior paint | H93: R | I93: -1575 | J93: -1575 | K93: -1575 | M93: REPAIR | N93: 7 | P93: 2002
B94: 37480 | C94: Huntington Checking-Ralston Checking | D94: 138 | E94: Terry Electric | F94: electric work | H94: R | I94: -850 | J94: -850 | K94: -850 | M94: ROOFING | N94: 204 | P94: 2002
B95: 37483 | C95: Marvel MC | D95: DC | E95: Lowe's | F95: bathroom light return | H95: R | I95: 52.49 | K95: 52.49 | M95: SHOWER DOOR | N95: 58 | P95: 2002
B96: 37487 | C96: Home Equity-Home Equity | E96: Finance Charges | H96: R | I96: -24.16 | J96: -24.16 | K96: -24.16 | M96: SIDING | N96: 104 | P96: 2002
B97: 37489 | C97: Marvel MC | D97: DC | E97: Amarr | F97: garage door & opener | H97: R | I97: -649.99 | J97: -649.99 | K97: -649.99 | M97: STEEL | N97: 24 | P97: 2002
B98: 37489 | C98: Marvel MC | D98: DC | E98: Dave's Trucking | F98: dumpster | H98: R | I98: -340 | J98: -340 | K98: -340 | M98: STRUCTURAL ENGINEERING | N98: 1 | P98: 2002
B99: 37490 | C99: Home Equity-Home Equity | D99: 1009 | E99: Flow-Rite | F99: gutters | H99: R | I99: -469.14 | J99: -469.14 | K99: -469.14 | M99: STUCCO | N99: 7 | P99: 2002
F100: range hood | G100: APPLIANCE INSTALL | H100: R | I100: -120 | J100: -120 | K100: -120 | M100: TILE | N100: 491 | P100: 1900
B101: 37490 | C101: Travis T-Amount Owed | D101: DC | E101: Lowe's | F101: nail gun | I101: 225 | K101: 225 | M101: TILE LABOR | N101: 101 | P101: 2002
B102: 37491 | C102: Home Equity-Home Equity | D102: 1012 | E102: Rodney Leighty | F102: window wrap payment | H102: R | I102: -800 | J102: -800 | K102: -800 | M102: TILE MATERIALS | N102: 187 | P102: 2002
F103: duct micro | G103: APPLIANCE INSTALL | H103: R | I103: -120 | J103: -120 | K103: -120 | M103: TOOL RENTAL | N103: 3 | P103: 1900
B104: 37491 | C104: Marvel MC | D104: DC | E104: Lowe's | F104: cabinet pulls | H104: R | I104: -162.44 | J104: -162.44 | K104: -162.44 | M104: TOOLS | N104: 3 | P104: 2002
...

Sheet timeline
A1: Milestones | B1: 45689 | C1: 45696 | D1: 45703 | E1: 45710 | F1: 45717 | G1: 45724 | H1: 45731 | I1: 45738 | J1: 45745 | K1: 45752 | L1: 45759 | M1: 45766 | N1: 45773 | O1: 45780
A2: Phase 1
A3: Make Timeline
A4: Gather Data
A5: Data Cleanup
A6: Consolidate Data
A7: Phase 2
A8: Visualization
A9: Identify Trends
A10: Report Insights
A11: Phase 3
A12: Develop Website
A13: Mapping
... A17: Final Project

Sheet totals
A1: Date | B1: Original Payee | C1: Last Name | D1: Amount | E1: Address | F1: Zip Code | H1: Row Labels | I1: Count of Zip Code
A2: TT Renovations | B2: 4039 Central | C2: Central | D2: -7538.26 | E2: 4039 Central Ave. | F2: 46205 | H2: 46013 | I2: 1
A3: TT Renovations | B3: 47th St. | C3: 47th | D3: -56134.38 | E3: 326 E 47th St | F3: 46205 | H3: 46032 | I3: 3
A4: TT Renovations | B4: Beverly Olsen (Abelard Co.) | C4: Olsen | D4: -3200 | E4: 13295 Illinois St | F4: 46032 | H4: 46033 | I4: 7
A5: TT Renovations | B5: Aimee Kandrac | C5: Yockey | D5: -130530.43 | E5: =VLOOKUP(C5,addresses!B:C,2,FALSE) -> 5325 Central Ave. | F5: =VLOOKUP(C5,addresses!B:D,3,FALSE) -> 46220 | H5: 46037 | I5: 2
A6: TT Renovations | B6: Mary Ajamie | C6: Ajamie | D6: -13354.71 | E6: =VLOOKUP(C6,addresses!B:C,2,FALSE) -> 4521 Pennsylvania St. | F6: 46205 | H6: 46077 | I6: 2
A7: TT Renovations | B7: Allen | C7: Tunstall | D7: -4506.86 | E7: 5645 Ralston Ave. | F7: 46220 | H7: 46201 | I7: 1
A8: TT Renovations | B8: Angelo | C8: Brown | D8: -2468.81 | E8: =VLOOKUP(C8,addresses!B:C,2,FALSE) -> 254 Hampton Dr. | F8: 46208 | H8: 46202 | I8: 4
A9: TT Renovations | B9: Arbour | C9: Arbour | D9: -956.09 | E9: =VLOOKUP(C9,addresses!B:C,2,FALSE) -> 4928 Central Ave. | F9: =VLOOKUP(C9,addresses!B:D,3,FALSE) -> 46205 | H9: 46205 | I9: 41
A10: TT Renovations | B10: Bella | C10: Bella | D10: -379.49 | E10: 3915 Winding Way | F10: 46220 | H10: 46206 | I10: 1
A11: TT Renovations | B11: Basch | C11: Basch | D11: -28468.99 | E11: =VLOOKUP(C11,addresses!B:C,2,FALSE) -> 1135 Ivy Lane | F11: =VLOOKUP(C11,addresses!B:D,3,FALSE) -> 46220 | H11: 46208 | I11: 17
A12: TT Renovations | B12: Baugh | C12: Baugh | D12: -8355.63 | E12: =VLOOKUP(C12,addresses!B:C,2,FALSE) -> 11125 Moss Dr. | F12: =VLOOKUP(C12,addresses!B:D,3,FALSE) -> 46033 | H12: 46220 | I12: 75
A13: TT Renovations | B13: Blueridge | C13: Blueridge | D13: -10677.12 | E13: 119 Blue Ridge Rd | F13: 46208 | H13: 46240 | I13: 2
A14: TT Renovations | B14: Jeff Bontrager | C14: Bontrager | D14: -715.32 | E14: 5734 Ralston Ave | F14: 46220 | H14: 46260 | I14: 6
A15: TT Renovations | B15: Bokelman | C15: Bokelman | D15: -11707.2 | E15: =VLOOKUP(C15,addresses!B:C,2,FALSE) -> 5401 Illinois St. | F15: =VLOOKUP(C15,addresses!B:D,3,FALSE) -> 46220 | H15: 46280 | I15: 1
A16: TT Renovations | B16: Brad Donaldson | C16: Donaldson | D16: -2020.49 | E16: =VLOOKUP(C16,addresses!B:C,2,FALSE) -> 1403 Kessler Blvd E Drive | F16: =VLOOKUP(C16,addresses!B:D,3,FALSE) -> 46220 | H16: Grand Total | I16: 163
A17: TT Renovations | B17: Brar | C17: Brar | D17: -55259.86 | E17: =VLOOKUP(C17,addresses!B:C,2,FALSE) -> 120 Bow Lane St. | F17: =VLOOKUP(C17,addresses!B:D,3,FALSE) -> 46220
A18: TT Renovations | B18: Jody Tetrault | C18: Tetrault | D18: -61510.3 | E18: 5923 Broadway St. | F18: 46220
A19: TT Renovations | B19: Holly Brooks | C19: Brooks | D19: -524.93 | E19: =VLOOKUP(C19,addresses!B:C,2,FALSE) -> #N/A | F19: =VLOOKUP(C19,addresses!B:D,3,FALSE) -> #N/A
A20: TT Renovations | B20: Brigance | C20: Brigance | D20: -14812.63 | E20: =VLOOKUP(C20,addresses!B:C,2,FALSE) -> 8455 Washington Blvd. | F20: =VLOOKUP(C20,addresses!B:D,3,FALSE) -> 46240
A21: TT Renovations | B21: Brim | C21: Brim | D21: -136245.09 | E21: =VLOOKUP(C21,addresses!B:C,2,FALSE) -> 4545 Central Ave | F21: =VLOOKUP(C21,addresses!B:D,3,FALSE) -> 46205
A22: TT Renovations | B22: Buggs.Cheng | C22: Cheng | D22: -599661.58 | E22: 5751 Central Ave. | F22: 46220
A23: TT Renovations | B23: Busto | C23: Busto | D23: -3981.82 | E23: =VLOOKUP(C23,addresses!B:C,2,FALSE) -> 3960 Delaware St. | F23: =VLOOKUP(C23,addresses!B:D,3,FALSE) -> 46202
A24: TT Renovations | B24: CDavis | C24: CDavis | D24: -32162.51 | E24: 1032 Foxglove Circle | F24: 46033
A25: TT Renovations | B25: Central | C25: Central | D25: -50057.63 | E25: 5373 Central Ave. | F25: 46220
A26: TT Renovations | B26: Jason Chappell | C26: Chappel | D26: 190.75 | E26: =VLOOKUP(C26,addresses!B:C,2,FALSE) -> #N/A | F26: =VLOOKUP(C26,addresses!B:D,3,FALSE) -> #N/A
A27: TT Renovations | B27: Christy & Jen | C27: Christy | D27: -397.38 | E27: 326 E 47th St | F27: 46205
A28: TT Renovations | B28: Brian Clay | C28: Clay | E28: 3580 Kessler Blvd East Dr | F28: 46220
A29: TT Renovations | B29: Brian Coles | C29: Coles | E29: 5445 Crestview Dr | F29: 46220
A30: TT Renovations | B30: Colips | C30: Colips | D30: 199.73 | E30: =VLOOKUP(C30,addresses!B:C,2,FALSE) -> #N/A | F30: =VLOOKUP(C30,addresses!B:D,3,FALSE) -> #N/A
A31: TT Renovations | B31: Colleen Brown | C31: Brown | D31: -279265.12 | E31: 254 Hampton Dr. | F31: 46205
A32: TT Renovations | B32: Jennifer Day | C32: Day | D32: 659.44 | E32: =VLOOKUP(C32,addresses!B:C,2,FALSE) -> #N/A | F32: =VLOOKUP(C32,addresses!B:D,3,FALSE) -> #N/A
A33: TT Renovations | B33: DbInteriors | C33: DbInteriors | D33: -3410.8 | E33: 4320 N Meridian St | F33: 46208
A34: TT Renovations | B34: Cornforth | C34: Cornforth | D34: -2182.22 | E34: =VLOOKUP(C34,addresses!B:C,2,FALSE) -> 245 Blue Ridge Rd. | F34: =VLOOKUP(C34,addresses!B:D,3,FALSE) -> 46205
A35: TT Renovations | B35: Cseszko | C35: Cseszko | D35: -7335.39 | E35: =VLOOKUP(C35,addresses!B:C,2,FALSE) -> 4527 Pennsylvania St. | F35: =VLOOKUP(C35,addresses!B:D,3,FALSE) -> 46205
A36: TT Renovations | B36: Damon Lettich | C36: Lettich | D36: -397.05 | E36: =VLOOKUP(C36,addresses!B:C,2,FALSE) -> 4848 Central Ave | F36: =VLOOKUP(C36,addresses!B:D,3,FALSE) -> 46205
A37: TT Renovations | B37: Davey | C37: Davey | D37: -197685.29 | E37: =VLOOKUP(C37,addresses!B:C,2,FALSE) -> 4134 Pennsylvania St | F37: =VLOOKUP(C37,addresses!B:D,3,FALSE) -> 46260
A38: TT Renovations | B38: DePaw | C38: DePaw | D38: 614.41 | E38: =VLOOKUP(C38,addresses!B:C,2,FALSE) -> #N/A | F38: =VLOOKUP(C38,addresses!B:D,3,FALSE) -> #N/A
A39: TT Renovations | B39: Demilt | C39: Demilt | D39: -64481.99 | E39: =VLOOKUP(C39,addresses!B:C,2,FALSE) -> 5520 N Meridian St | F39: =VLOOKUP(C39,addresses!B:D,3,FALSE) -> 46208
A40: TT Renovations | B40: Demotte | C40: Demotte | D40: -80744.33 | E40: =VLOOKUP(C40,addresses!B:C,2,FALSE) -> 5421 N Pennsylvania St. | F40: =VLOOKUP(C40,addresses!B:D,3,FALSE) -> 46220
A41: TT Renovations | B41: John Diercks Sr. | C41: Diercks Sr. | D41: -29487.68 | E41: 5254 Broadway St. | F41: 46220
A42: TT Renovations | B42: Perfect Blue Buildings (Dover) | C42: Dover | D42: -348058.02 | E42: =VLOOKUP(C42,addresses!B:C,2,FALSE) -> 6445 Dover Rd. | F42: =VLOOKUP(C42,addresses!B:D,3,FALSE) -> 46220
A43: TT Renovations | B43: Drew | C43: Drew | D43: 761.24 | E43: =VLOOKUP(C43,addresses!B:C,2,FALSE) -> #N/A | F43: =VLOOKUP(C43,addresses!B:D,3,FALSE) -> #N/A
A44: TT Renovations | B44: Matt Durham | C44: Durham | D44: -883.42 | E44: 5883 Crestview Ave. | F44: 46220
A45: TT Renovations | B45: El-Afandi Jackson | C45: Jackson | D45: -33311.85 | E45: =VLOOKUP(C45,addresses!B:C,2,FALSE) -> 5760 Guilford Ave | F45: =VLOOKUP(C45,addresses!B:D,3,FALSE) -> 46220
A46: TT Renovations | B46: Egan | C46: Egan | D46: -105099.84 | E46: =VLOOKUP(C46,addresses!B:C,2,FALSE) -> 5539 Fall Creek Rd. | F46: =VLOOKUP(C46,addresses!B:D,3,FALSE) -> 46220
A47: TT Renovations | B47: Chris & Paige Evans | C47: Evans | D47: 85 | E47: =VLOOKUP(C47,addresses!B:C,2,FALSE) -> #N/A | F47: =VLOOKUP(C47,addresses!B:D,3,FALSE) -> #N/A
A48: TT Renovations | B48: Engel | C48: Engel | D48: -63764.56 | E48: =VLOOKUP(C48,addresses!B:C,2,FALSE) -> 5829 N Lasalle St. | F48: =VLOOKUP(C48,addresses!B:D,3,FALSE) -> 46220
A49: TT Renovations | B49: Engelhardt | C49: Engelhardt | D49: -20559.47 | E49: =VLOOKUP(C49,addresses!B:C,2,FALSE) -> 5341 Central Ave | F49: =VLOOKUP(C49,addresses!B:D,3,FALSE) -> 46220
A50: TT Renovations | B50: Farrell | C50: Farrell | D50: -15748.11 | E50: =VLOOKUP(C50,addresses!B:C,2,FALSE) -> 5934 Crittenden Ave. | F50: =VLOOKUP(C50,addresses!B:D,3,FALSE) -> 46220
A51: TT Renovations | B51: Fisher | C51: Fisher | D51: -1507.09 | E51: =VLOOKUP(C51,addresses!B:C,2,FALSE) -> 5643 Washington Blvd | F51: =VLOOKUP(C51,addresses!B:D,3,FALSE) -> 46220
A52: TT Renovations | B52: Floy | C52: Floy | E52: 5927 Broadway St. | F52: 46220
A53: TT Renovations | B53: Christine Freeman | C53: Freeman | D53: -416.45 | E53: 4906 Central Ave | F53: 46205
A54: TT Renovations | B54: French | C54: French | D54: -1860.61 | E54: =VLOOKUP(C54,addresses!B:C,2,FALSE) -> 725 E. 58th St. | F54: =VLOOKUP(C54,addresses!B:D,3,FALSE) -> 46220
A55: TT Renovations | B55: Gable | C55: Gable | D55: -15678.91 | E55: =VLOOKUP(C55,addresses!B:C,2,FALSE) -> 201 Blue Ridge Rd. | F55: =VLOOKUP(C55,addresses!B:D,3,FALSE) -> 46208
A56: TT Renovations | B56: Barbara Danner | C56: Danner | D56: -32391.73 | E56: =VLOOKUP(C56,addresses!B:C,2,FALSE) -> 4160 Washington Blvd | F56: =VLOOKUP(C56,addresses!B:D,3,FALSE) -> 46205
A57: TT Renovations | B57: Gilroy | C57: Gilroy | D57: -18179.41 | E57: =VLOOKUP(C57,addresses!B:C,2,FALSE) -> 4462 Delaware St. | F57: =VLOOKUP(C57,addresses!B:D,3,FALSE) -> 46205
A58: TT Renovations | B58: Glenn | C58: Glenn | D58: -23459.08 | E58: =VLOOKUP(C58,addresses!B:C,2,FALSE) -> 1837 Spruce Dr. | F58: =VLOOKUP(C58,addresses!B:D,3,FALSE) -> 46033
A59: TT Renovations | B59: Goth | C59: Goth | D59: -13425.16 | E59: =VLOOKUP(C59,addresses!B:C,2,FALSE) -> 5352 Central Ave | F59: =VLOOKUP(C59,addresses!B:D,3,FALSE) -> 46220
A60: TT Renovations | B60: Greene | C60: Greene | D60: -58397.19 | E60: =VLOOKUP(C60,addresses!B:C,2,FALSE) -> 3953 N. New Jersey | F60: =VLOOKUP(C60,addresses!B:D,3,FALSE) -> 46205
A61: TT Renovations | B61: Greer | C61: Greer | D61: -170365.6 | E61: =VLOOKUP(C61,addresses!B:C,2,FALSE) -> 6545 N. Olney St. | F61: =VLOOKUP(C61,addresses!B:D,3,FALSE) -> 46220
A62: TT Renovations | B62: TTRenovations HQ (Garage) | C62: HQ | D62: -2872.15 | E62: 1225 E 54th St. | F62: 46220
A63: TT Renovations | B63: Gregory | C63: Gregory | D63: -257470.26 | E63: =VLOOKUP(C63,addresses!B:C,2,FALSE) -> 505 W. Sycamore St. | F63: =VLOOKUP(C63,addresses!B:D,3,FALSE) -> 46077
A64: TT Renovations | B64: Grise | C64: Grise | D64: -1517.46 | E64: =VLOOKUP(C64,addresses!B:C,2,FALSE) -> 6360 Burlington Ave. | F64: =VLOOKUP(C64,addresses!B:D,3,FALSE) -> 46220
A65: TT Renovations | B65: Gritton | C65: Gritton | D65: -107974.57 | E65: =VLOOKUP(C65,addresses!B:C,2,FALSE) -> 133 E 44th St | F65: =VLOOKUP(C65,addresses!B:D,3,FALSE) -> 46205
A66: TT Renovations | B66: Groves.House | C66: Groves.House | D66: -230588.42 | E66: 5877 Crestview Ave | F66: 46220
A67: TT Renovations | B67: Jon Gubera & Caroline Hunt | C67: Gubera | D67: -73299.44 | E67: =VLOOKUP(C67,addresses!B:C,2,FALSE) -> 433 Pennridge Dr. | F67: =VLOOKUP(C67,addresses!B:D,3,FALSE) -> 46240
A68: TT Renovations | B68: Hadar | C68: Hadar | D68: -68630.84 | E68: =VLOOKUP(C68,addresses!B:C,2,FALSE) -> 5221 Cornelius Ave. | F68: =VLOOKUP(C68,addresses!B:D,3,FALSE) -> 46208
A69: TT Renovations | B69: Hampton | C69: Hampton | D69: -87558.27 | E69: 228 W Hampton Dr | F69: 46208
A70: TT Renovations | B70: Harris | C70: Harris | D70: -39129.11 | E70: =VLOOKUP(C70,addresses!B:C,2,FALSE) -> 301 Buckingham Dr. | F70: =VLOOKUP(C70,addresses!B:D,3,FALSE) -> 46208
A71: TT Renovations | B71: Hayward | C71: Hayward | D71: -9055.03 | E71: =VLOOKUP(C71,addresses!B:C,2,FALSE) -> 5119 Broadway St. | F71: =VLOOKUP(C71,addresses!B:D,3,FALSE) -> 46205
A72: TT Renovations | B72: Hege | C72: Hege | D72: -57145.85 | E72: =VLOOKUP(C72,addresses!B:C,2,FALSE) -> 5155 Central Ave | F72: =VLOOKUP(C72,addresses!B:D,3,FALSE) -> 46220
A73: TT Renovations | B73: Hendrickson | C73: Hendrickson | D73: -55756.26 | E73: =VLOOKUP(C73,addresses!B:C,2,FALSE) -> 4301 Park Ave. | F73: =VLOOKUP(C73,addresses!B:D,3,FALSE) -> 46205
A74: TT Renovations | B74: Hillenburg | C74: Hillenburg | D74: -2814.73 | E74: =VLOOKUP(C74,addresses!B:C,2,FALSE) -> 5760 N. Pennsylvania St. | F74: =VLOOKUP(C74,addresses!B:D,3,FALSE) -> 46220
A75: TT Renovations | B75: Greg Hardesty | C75: Hardesty | D75: -126.19 | E75: 4907 N College Ave. | F75: 46205
A76: TT Renovations | B76: Jeff Hauk | C76: Hauk | D76: 3659.81 | E76: =VLOOKUP(C76,addresses!B:C,2,FALSE) -> #N/A | F76: =VLOOKUP(C76,addresses!B:D,3,FALSE) -> #N/A
A77: TT Renovations | B77: Hinds | C77: Hinds | D77: 555 | E77: =VLOOKUP(C77,addresses!B:C,2,FALSE) -> #N/A | F77: =VLOOKUP(C77,addresses!B:D,3,FALSE) -> #N/A
A78: TT Renovations | B78: Holmes | C78: Holmes | D78: -62388.54 | E78: =VLOOKUP(C78,addresses!B:C,2,FALSE) -> 1468 N Alabama St | F78: =VLOOKUP(C78,addresses!B:D,3,FALSE) -> 46202
A79: TT Renovations | B79: Horn | C79: Horn | D79: -289130.19 | E79: =VLOOKUP(C79,addresses!B:C,2,FALSE) -> 5746 Central Ave | F79: =VLOOKUP(C79,addresses!B:D,3,FALSE) -> 46220
A80: TT Renovations | B80: Horst | C80: Horst | D80: -214244.1 | E80: =VLOOKUP(C80,addresses!B:C,2,FALSE) -> 4456 Park Ave | F80: =VLOOKUP(C80,addresses!B:D,3,FALSE) -> 46208
A81: TT Renovations | B81: Houle | C81: Houle | D81: -6900 | E81: =VLOOKUP(C81,addresses!B:C,2,FALSE) -> 5131 Park Ave | F81: =VLOOKUP(C81,addresses!B:D,3,FALSE) -> 46220
A82: TT Renovations | B82: Chad & Angie Hobson | C82: Hobson | D82: 750.61 | E82: =VLOOKUP(C82,addresses!B:C,2,FALSE) -> #N/A | F82: =VLOOKUP(C82,addresses!B:D,3,FALSE) -> #N/A
A83: TT Renovations | B83: Julia Holliday & John Rhoden | C83: Rhoden | D83: -40356.94 | E83: =VLOOKUP(C83,addresses!B:C,2,FALSE) -> 5117 N Park Ave. | F83: =VLOOKUP(C83,addresses!B:D,3,FALSE) -> 46205
A84: TT Renovations | B84: Perfect Blue Buildings (Illinois) | C84: Illinois | D84: -534627.78 | E84: =VLOOKUP(C84,addresses!B:C,2,FALSE) -> 7365 N Illinois St. | F84: =VLOOKUP(C84,addresses!B:D,3,FALSE) -> 46260
A85: TT Renovations | B85: Jay Anderson | C85: Anderson | D85: -3389.08 | E85: 6049 Central Ave. | F85: 46220
A86: TT Renovations | B86: Jeff's house | C86: Jeff's | D86: -14807.2 | E86: 5734 Ralston Ave | F86: 46220
A87: TT Renovations | B87: Jimmy | C87: Jimmy | D87: 175 | E87: =VLOOKUP(C87,addresses!B:C,2,FALSE) -> #N/A | F87: =VLOOKUP(C87,addresses!B:D,3,FALSE) -> #N/A
A88: TT Renovations | B88: Bill Jones | C88: Jones | D88: -4056.77 | E88: =VLOOKUP(C88,addresses!B:C,2,FALSE) -> 430 N Park Ave | F88: =VLOOKUP(C88,addresses!B:D,3,FALSE) -> 46202
A89: TT Renovations | B89: JonP | C89: JonP | D89: 1903.76 | E89: =VLOOKUP(C89,addresses!B:C,2,FALSE) -> #N/A | F89: =VLOOKUP(C89,addresses!B:D,3,FALSE) -> #N/A
A90: TT Renovations | B90: Lynn Kahl | C90: Kahl | D90: 1385 | E90: =VLOOKUP(C90,addresses!B:C,2,FALSE) -> #N/A | F90: =VLOOKUP(C90,addresses!B:D,3,FALSE) -> #N/A
A91: TT Renovations | B91: Fran Kandrac | C91: Kandrac | D91: -4672.65 | E91: 10800 Belair Dr | F91: 46280
A92: TT Renovations | B92: Pat Keifer | C92: Keifer | D92: -10222.88 | E92: 5868 Washington Blvd | F92: 46220
A93: TT Renovations | B93: Susan Kessler | C93: Kessler | D93: 575 | E93: =VLOOKUP(C93,addresses!B:C,2,FALSE) -> #N/A | F93: =VLOOKUP(C93,addresses!B:D,3,FALSE) -> #N/A
A94: TT Renovations | B94: Victoria Lee & Mike Stiers | C94: Stiers | D94: -45577.39 | E94: =VLOOKUP(C94,addresses!B:C,2,FALSE) -> 6420 Brokenhurst Rd | F94: =VLOOKUP(C94,addresses!B:D,3,FALSE) -> 46220
A95: TT Renovations | B95: Monica&Marty Lewis | C95: Lewis | D95: -272.37 | E95: 5922 Broadway St | F95: 46220
A96: TT Renovations | B96: Kastner | C96: Kastner | D96: -40620.4 | E96: =VLOOKUP(C96,addresses!B:C,2,FALSE) -> 5135 Central Ave | F96: =VLOOKUP(C96,addresses!B:D,3,FALSE) -> 46220
A97: TT Renovations | B97: Kathy Churchman | C97: Churchman | D97: -384.41 | E97: =VLOOKUP(C97,addresses!B:C,2,FALSE) -> Washington Blvd. | F97: =VLOOKUP(C97,addresses!B:D,3,FALSE) -> 46220
A98: TT Renovations | B98: Katner | C98: Katner | D98: -10059.21 | E98: =VLOOKUP(C98,addresses!B:C,2,FALSE) -> 6215 Central Ave. | F98: =VLOOKUP(C98,addresses!B:D,3,FALSE) -> 46220
A99: TT Renovations | B99: Kelley | C99: Kelley | D99: -342972.37 | E99: =VLOOKUP(C99,addresses!B:C,2,FALSE) -> 5699 Winthrop Ave | F99: =VLOOKUP(C99,addresses!B:D,3,FALSE) -> 46220
A100: TT Renovations | B100: Kleiman | C100: Kleiman | D100: -67233.96 | E100: =VLOOKUP(C100,addresses!B:C,2,FALSE) -> 9534 Copley Dr. | F100: =VLOOKUP(C100,addresses!B:D,3,FALSE) -> 46260
...

Sheet addresses
A1: Payee | B1: Last Name | C1: Street | D1: Zip | E1: City | F1: State
A2: Mary Ajamie | B2: Ajamie | C2: 4521 Pennsylvania St. | D2: 46205 | E2: Indianapolis | F2: IN
A3: Davina Arbour | B3: Arbour | C3: 4928 Central Ave. | D3: 46205 | E3: Indianapolis | F3: IN
A4: Kim Basch | B4: Basch | C4: 1135 Ivy Lane | D4: 46220 | E4: Indianapolis | F4: IN
A5: Gene & Sharon Baugh | B5: Baugh | C5: 11125 Moss Dr. | D5: 46033 | E5: Carmel | F5: IN
A6: Beau & Kristin Bokelman | B6: Bokelman | C6: 5401 Illinois St. | D6: 46220 | E6: Indianapolis | F6: IN
A7: Aman & Susan Brar | B7: Brar | C7: 120 Bow Lane St. | D7: 46220 | E7: Indianapolis | F7: IN
A8: Steve & Anne Brigance | B8: Brigance | C8: 8455 Washington Blvd. | D8: 46240 | E8: Indianapolis | F8: IN
A9: Nate & Laura Brim | B9: Brim | C9: 4545 Central Ave | D9: 46205 | E9: Indianapolis | F9: IN
A10: Colleen Brown | B10: Brown | C10: 254 Hampton Dr. | D10: 46208 | E10: Indianapolis | F10: IN
A11: Juan & Sheila Brown | B11: Brown | C11: 5740 Central Ave | D11: 46220 | E11: Indianapolis | F11: IN
A12: MaryEllen Brown | B12: Brown | C12: 38 W 59th St | D12: 46208 | E12: Indianapolis | F12: IN
A13: Kathy Busto | B13: Busto | C13: 3960 Delaware St. | D13: 46202 | E13: Indianapolis | F13: IN
... A64: Bill Jones | B64: Jones | C64: 430 N Park Ave | D64: 46202 | E64: Indianapolis | F64: IN
A65: Fran Kandrac | B65: Kandrac
A66: Kevin & Sara Kastner | B66: Kastner | C66: 5135 Central Ave | D66: 46220 | E66: Indianapolis | F66: IN
A67: Jason & Gretchen Katner | B67: Katner | C67: 6215 Central Ave. | D67: 46220 | E67: Indianapolis | F67: IN
A68: Brad & Cassie Kelley | B68: Kelley | C68: 5699 Winthrop Ave | D68: 46220 | E68: Indianapolis | F68: IN
A69: John Vanausdall & Carrie Kirk | B69: Kirk | C69: 4535 N Park Ave | D69: 46205 | E69: Indianapolis | F69: IN
A70: Seth & Amanda Kleiman | B70: Kleiman | C70: 9534 Copley Dr. | D70: 46260 | E70: Indianapolis | F70: IN
A71: John & Rebecca Klein | B71: Klein | C71: 4424 Central Ave | D71: 46205 | E71: Indianapolis | F71: IN
A72: Mike & Michelle Knight | B72: Knight | C72: 121 E 51st St | D72: 46205 | E72: Indianapolis | F72: IN
A73: Dan & Chelsea Koehring | B73: Koehring | C73: 3917 New Jersey St. | D73: 46205 | E73: Indianapolis | F73: IN
A74: Kevin & Mary Beth Kohart | B74: Kohart | C74: 5130 Pennsylvania St. | D74: 46205 | E74: Indianapolis | F74: IN
A75: Bryon & Christine Konvolinka | B75: Konvolinka | C75: 5639 Washington Blvd. | D75: 46220 | E75: Indianapolis | F75: IN
A76: Nick Koon | B76: Koon | C76: 5137 Broadway St | D76: 46205 | E76: Indianapolis | F76: IN
A77: Maggie & Aaron Lasley | B77: Lasley | C77: 1 Stone Wall Ln. | D77: 46077 | E77: Zionsville | F77: IN
... A87: JoAnn Maze | B87: Maze | C87: 5325 N Delaware St | D87: 46220 | E87: Indianapolis | F87: IN
A88: Matt McMichael | B88: McMichael
A89: Jack & Candice Mees | B89: Mees | C89: 4717 Graceland Ave. | D89: 46208 | E89: Indianapolis | F89: IN
A90: Nadine Melind | B90: Melind | C90: 5131 Central Ave. | D90: 46220 | E90: Indianapolis | F90: IN
A91: Joanna & Hap Milliken | B91: Milliken | C91: 412 48th St | D91: 46220 | E91: Indianapolis | F91: IN
A92: Anne Mc Callister Mills | B92: Mills | C92: 6120 N Delaware St. | D92: 46220 | E92: Indianapolis | F92: IN
A93: Phil & Olympia Ming | B93: Ming | C93: 15646 Bridgewater Club Blvd. | D93: 46033 | E93: Carmel | F93: IN
A94: Ray & Dianne Montagno | B94: Montagno | C94: 12276 Charing Cross Rd. | D94: 46033 | E94: Carmel | F94: IN
A95: Gareth & Pam Morgan | B95: Morgan | C95: 4348 48th St. | D95: 46220 | E95: Indianapolis | F95: IN
A96: Ted & Caroline Mosey | B96: Mosey | C96: 4631 N Park Ave | D96: 46205 | E96: Indianapolis | F96: IN
A97: Mike Musson | B97: Musson | C97: 5219 N College Ave | D97: 46205 | E97: Indianapolis | F97: IN
A98: Paul & Michele Musson | B98: Musson | C98: 4545 Delaware St. | D98: 46208 | E98: Indianapolis | F98: In
A99: Paul Musson | B99: Musson | C99: 4545 N Delaware St. | D99: 46205 | E99: Indianapolis | F99: IN
A100: Ward Myers | B100: Myers | C100: 47 E 52nd St | D100: 46205 | E100: Indianapolis | F100: IN
... A132: Richard & Shereen Zellars | B132: Zellars | C132: 723 East St. | D132: 46202 | E132: Indianapolis | F132: IN
A133: 38th St. Stor-N-Loc | C133: 504 E. 38th St. | D133: 46013 | E133: Anderson | F133: IN
